markov362m/__init__.py
markov362m/_classes.py
markov362m/_representation.py
markov362m/base.py
markov362m/constructions.py
markov362m/examples.py
markov362m/io.py
markov362m/simulation.py
markov362m/utilities.py
markov362m-0.0.10.dist-info/LICENSE
markov362m-0.0.10.dist-info/METADATA
markov362m-0.0.10.dist-info/WHEEL
markov362m-0.0.10.dist-info/top_level.txt
markov362m-0.0.10.dist-info/RECORD
