Metadata-Version: 2.1
Name: markov362m
Version: 0.0.10
Summary: A Markov-chain class for M362M
Home-page: https://github.com/gordanz/Markov362M
Author: Gordan Zitkovic
Author-email: gordanz@math.utexas.edu
License: UNKNOWN
Project-URL: Source, https://github.com/gordanz/MarkovM362M/
Platform: UNKNOWN
Requires-Python: >=3.5, <4
Requires-Dist: networkx (>=2.3)
Requires-Dist: numpy
Requires-Dist: scipy
